gnayt-0.1.3.dist-info/DESCRIPTION.rst
gnayt-0.1.3.dist-info/METADATA
gnayt-0.1.3.dist-info/RECORD
gnayt-0.1.3.dist-info/WHEEL
gnayt-0.1.3.dist-info/entry_points.txt
gnayt-0.1.3.dist-info/metadata.json
gnayt-0.1.3.dist-info/top_level.txt
gnayt-0.1.3.dist-info/zip-safe
me/__init__.py
me/me.py
