Metadata-Version: 2.0
Name: gnayt
Version: 0.1.3
Summary: desc me
Home-page: UNKNOWN
Author: yang
Author-email: UNKNOWN
License: UNKNOWN
Keywords: me
Platform: UNKNOWN
